Workbook

Sheet Renda Julho
C3: Controle Financeiro
C6: RENDA MENSAL
C7: Renda 1 | D7: 1800
C8: Renda 2 | D8: 1400
C9: Renda total mensal | D9: =D7+D8 -> 3200
C11: DÍVIDA 1 | E11: DÍVIDA 2 - Loja Aurora | G11: DÍVIDA 3 - Loja Nimbus
C12: Valor total da dívida | D12: 8500 | E12: Valor total da dívida | F12: 96 | G12: Valor total da dívida | H12: 96
C13: Nº de parcelas restantes | D13: 9 | E13: Nº de parcelas restantes | F13: 1 | G13: Nº de parcelas restantes | H13: 1
C14: Valor da parcela mensal | D14: 800 | E14: Valor da parcela mensal | F14: 49 | G14: Valor da parcela mensal | H14: 43
C15: % da renda comprometida | D15: =D14/D9 -> 0.25
C16: Quanto ainda falta: | D16: =D12 -> 8500
C18: DISPONÍVEL PARA GASTAR
C19: Renda total | D19: =D9 -> 3200
C20: (-) Parcela da dívida | D20: =F14+H14+D14 -> 892
C21: Valor Disponível Mensal | D21: =D19-D20 -> 2308

Sheet Renda Agosto
C3: Controle Financeiro
C6: RENDA MENSAL
C7: Renda 1 | D7: 1800
C8: Renda 2 | D8: 1400
C9: Renda total mensal | D9: =D7+D8 -> 3200
C11: DÍVIDA 1 | E11: DÍVIDA 2 - Loja Aurora | G11: DÍVIDA 3 - Loja Nimbus
C12: Valor total da dívida | D12: 8500 | E12: Valor parcela atual | F12: 47 | G12: Valor parcela atual | H12: 19
C13: Nº de parcelas restantes | D13: 8
C14: Valor da parcela mensal | D14: 1180
C15: % da renda comprometida | D15: =D14/D9 -> 0.36875
C16: Quanto ainda falta: | D16: ='Renda Julho'!D16-D14 -> 7320
C18: DISPONÍVEL PARA GASTAR
C19: Renda total | D19: =D9 -> 3200
C20: (-) Parcela da dívida | D20: =D14+F12+H12 -> 1246
C21: Valor Disponível Mensal | D21: =D19-D20 -> 1954

Sheet Renda Setembro
C3: Controle Financeiro
C6: RENDA MENSAL
C7: Renda 1 | D7: 1800
C8: Renda 2 | D8: 1400
C9: Renda total mensal | D9: =D7+D8 -> 3200
C11: DÍVIDA 1
C12: Valor total da dívida | D12: 8500
C13: Nº de parcelas restantes | D13: 7
C14: Valor da parcela mensal | D14: 1150
C15: % da renda comprometida | D15: =D14/D9 -> 0.359375
C16: Quanto ainda falta: | D16: ='Renda Agosto'!D16-D14 -> 6170
C18: DISPONÍVEL PARA GASTAR
C19: Renda total | D19: =D9 -> 3200
C20: (-) Parcela da dívida | D20: =-D14 -> -1150
C21: Valor Disponível Mensal | D21: =D19+D20 -> 2050

Sheet Renda Outubro
C3: Controle Financeiro
C6: RENDA MENSAL
C7: Renda 1 | D7: 1800
C8: Renda 2 | D8: 1400
C9: Renda total mensal | D9: =D7+D8 -> 3200
C11: DÍVIDA 1
C12: Valor total da dívida | D12: 8500
C13: Nº de parcelas restantes | D13: 6
C14: Valor da parcela mensal | D14: 1070
C15: % da renda comprometida | D15: =D14/D9 -> 0.334375
C16: Quanto ainda falta: | D16: ='Renda Setembro'!D16-D14 -> 5100
C18: DISPONÍVEL PARA GASTAR
C19: Renda total | D19: =D9 -> 3200
C20: (-) Parcela da dívida | D20: =-D14 -> -1070
C21: Valor Disponível Mensal | D21: =D19+D20 -> 2130

Sheet Renda Novembro
C3: Controle Financeiro
C6: RENDA MENSAL
C7: Renda 1 | D7: 1800
C8: Renda 2 | D8: 1400
C9: Renda total mensal | D9: =D7+D8 -> 3200
C11: DÍVIDA 1
C12: Valor total da dívida | D12: 8500
C13: Nº de parcelas restantes | D13: 5
C14: Valor da parcela mensal | D14: 890
C15: % da renda comprometida | D15: =D14/D9 -> 0.278125
C16: Quanto ainda falta: | D16: ='Renda Outubro'!D16-D14 -> 4210
C18: DISPONÍVEL PARA GASTAR
C19: Renda total | D19: =D9 -> 3200
C20: (-) Parcela da dívida | D20: =-D14 -> -890
C21: Valor Disponível Mensal | D21: =D19+D20 -> 2310

Sheet Renda Dezembro
C3: Controle Financeiro
C6: RENDA MENSAL
C7: Renda 1 | D7: 1800
C8: Renda 2 | D8: 1400
C9: Renda total mensal | D9: =D7+D8 -> 3200
C11: DÍVIDA 1
C12: Valor total da dívida | D12: 8500
C13: Nº de parcelas restantes | D13: 4
C14: Valor da parcela mensal | D14: 890
C15: % da renda comprometida | D15: =D14/D9 -> 0.278125
C16: Quanto ainda falta: | D16: ='Renda Novembro'!D16-D14 -> 3320
C18: DISPONÍVEL PARA GASTAR
C19: Renda total | D19: =D9 -> 3200
C20: (-) Parcela da dívida | D20: =-D14 -> -890
C21: Valor Disponível Mensal | D21: =D19+D20 -> 2310

Sheet Renda Janeiro
C3: Controle Financeiro
C6: RENDA MENSAL
C7: Renda 1 | D7: 1800
C8: Renda 2 | D8: 1400
C9: Renda total mensal | D9: =D7+D8 -> 3200
C11: DÍVIDA 1
C12: Valor total da dívida | D12: 8500
C13: Nº de parcelas restantes | D13: 3
C14: Valor da parcela mensal | D14: 890
C15: % da renda comprometida | D15: =D14/D9 -> 0.278125
C16: Quanto ainda falta: | D16: ='Renda Dezembro'!D16-D14 -> 2430
C18: DISPONÍVEL PARA GASTAR
C19: Renda total | D19: =D9 -> 3200
C20: (-) Parcela da dívida | D20: =-D14 -> -890
C21: Valor Disponível Mensal | D21: =D19+D20 -> 2310

Sheet Renda Fevereiro
C3: Controle Financeiro
C6: RENDA MENSAL
C7: Renda 1 | D7: 1800
C8: Renda 2 | D8: 1400
C9: Renda total mensal | D9: =D7+D8 -> 3200
C11: DÍVIDA 1
C12: Valor total da dívida | D12: 8500
C13: Nº de parcelas restantes | D13: 2
C14: Valor da parcela mensal | D14: 810
C15: % da renda comprometida | D15: =D14/D9 -> 0.253125
C16: Quanto ainda falta: | D16: ='Renda Janeiro'!D16-D14 -> 1620
C18: DISPONÍVEL PARA GASTAR
C19: Renda total | D19: =D9 -> 3200
C20: (-) Parcela da dívida | D20: =-D14 -> -810
C21: Valor Disponível Mensal | D21: =D19+D20 -> 2390

Sheet Renda Março
C3: Controle Financeiro
C6: RENDA MENSAL
C7: Renda 1 | D7: 1800
C8: Renda 2 | D8: 1400
C9: Renda total mensal | D9: =D7+D8 -> 3200
C11: DÍVIDA 1
C12: Valor total da dívida | D12: 8500
C13: Nº de parcelas restantes | D13: 1
C14: Valor da parcela mensal | D14: 810
C15: % da renda comprometida | D15: =D14/D9 -> 0.253125
C16: Quanto ainda falta: | D16: ='Renda Fevereiro'!D16-D14 -> 810
C18: DISPONÍVEL PARA GASTAR
C19: Renda total | D19: =D9 -> 3200
C20: (-) Parcela da dívida | D20: =-D14 -> -810
C21: Valor Disponível Mensal | D21: =D19+D20 -> 2390

Sheet Renda Abril
C3: Controle Financeiro
C6: RENDA MENSAL
C7: Renda 1 | D7: 1800
C8: Renda 2 | D8: 1400
C9: Renda total mensal | D9: =D7+D8 -> 3200
C11: DÍVIDA 1
C12: Valor total da dívida | D12: 8500
C13: Nº de parcelas restantes | D13: Última parcela!!!
C14: Valor da parcela mensal | D14: 810
C15: % da renda comprometida | D15: =D14/D9 -> 0.253125
C16: Quanto ainda falta: | D16: ='Renda Março'!D16-D14 -> 0
C18: DISPONÍVEL PARA GASTAR
C19: Renda total | D19: =D9 -> 3200
C20: (-) Parcela da dívida | D20: =-D14 -> -810
C21: Valor Disponível Mensal | D21: =D19+D20 -> 2390

Sheet Gastos diários
C3: Controles mensais
C6: Mês | D6: Categoria | E6: Descrição | F6: Valor
C7: 46205 | D7: Alimentação | E7: Supermercado | F7: 210.5
C8: 46208 | D8: Transporte | E8: Aplicativo de transporte | F8: 28
C9: 46211 | D9: Outros | E9: Chaveiro | F9: 30
C10: 46212 | D10: Transporte | E10: Combustível | F10: 120
C11: 46212 | D11: Lazer | E11: Cinema | F11: 45
C12: 46217 | D12: Assinaturas | E12: Streaming de vídeo | F12: 120
C13: 46218 | D13: Alimentação | E13: Restaurante | F13: 85
C14: 46218 | D14: Outros | E14: Farmácia | F14: 60
C15: 46223 | D15: Transporte | E15: Aplicativo de transporte | F15: 32
C16: 46225 | D16: Alimentação | E16: Feira | F16: 95
C17: 46230 | D17: Lazer | E17: Show | F17: 150
C18: 46233 | D18: Assinaturas | E18: Inteligência Artificial | F18: 150

Sheet Gastos totais
C3: Gastos por Categoria
C5: Disponível para gastar julho: | D5: 2308
C7: Categoria | D7: Limite | E7: Gasto | F7: Sobra | G7: Status
C8: Alimentação | D8: 740 | E8: =SUMIF('Gastos diários'!D:D,C8,'Gastos diários'!F:F) -> 390.5 | F8: =IFERROR(D8-E8,"") -> 349.5 | G8: =IF(E8>D8,"Negativo","Ok") -> Ok
C9: Transporte | D9: 470 | E9: =SUMIF('Gastos diários'!D:D,C9,'Gastos diários'!F:F) -> 180 | F9: =IFERROR(D9-E9,"") -> 290 | G9: =IF(E9>D9,"Negativo","Ok") -> Ok
C10: Assinaturas | D10: 200 | E10: =SUMIF('Gastos diários'!D:D,C10,'Gastos diários'!F:F) -> 270 | F10: =IFERROR(D10-E10,"") -> -70 | G10: =IF(E10>D10,"Negativo","Ok") -> Negativo
C11: Lazer | D11: 560 | E11: =SUMIF('Gastos diários'!D:D,C11,'Gastos diários'!F:F) -> 195 | F11: =IFERROR(D11-E11,"") -> 365 | G11: =IF(E11>D11,"Negativo","Ok") -> Ok
C12: Outros | D12: 338 | E12: =SUMIF('Gastos diários'!D:D,C12,'Gastos diários'!F:F) -> 90 | F12: =IFERROR(D12-E12,"") -> 248 | G12: =IF(E12>D12,"Negativo","Ok") -> Ok
C13: TOTAL | D13: =SUM(D8:D12) -> 2308 | E13: =SUM(E8:E12) -> 1125.5 | F13: =SUM(F8:F12) -> 1182.5
D15: =D13-D14 -> 2308 | E15: =E13-E14 -> 1125.5
C16: Valor para investimento: | D16: =F13 -> 1182.5
